MANIFEST.in
README.rst
pinguinohandler.desktop
setup.py
bin/pinguinohandler
pinguinocloud/__init__.py
pinguinocloud/handler.py
pinguinocloud/info.py
pinguinocloud/login.py
pinguinocloud.egg-info/PKG-INFO
pinguinocloud.egg-info/SOURCES.txt
pinguinocloud.egg-info/dependency_links.txt
pinguinocloud.egg-info/not-zip-safe
pinguinocloud.egg-info/requires.txt
pinguinocloud.egg-info/top_level.txt
pinguinocloud/core/__init__.py
pinguinocloud/core/boards.py
pinguinocloud/core/config.py
pinguinocloud/core/pinguino.py
pinguinocloud/core/pinguino_config.py
pinguinocloud/core/pinguino_tools.py
pinguinocloud/core/uploader/__init__.py
pinguinocloud/core/uploader/autodetect.py
pinguinocloud/core/uploader/uploader.py
pinguinocloud/core/uploader/uploader32.py
pinguinocloud/core/uploader/uploader8.py
pinguinocloud/core/uploader/uploaderDLN.py
pinguinocloud/core/uploader/uploaderVSC.py