Metadata-Version: 1.1
Name: pinguinocloud
Version: 0.1.4
Summary: Open Hardware Electronics Prototyping Platform, Open Source Integrated Development Environment (IDE)
Home-page: http://www.pinguino.cc/
Author: Yeison Cardona
Author-email: yeison.eng@gmail.com
License: GPLv2
Keywords: microchip,electronic,prototyping,IDE
Platform: UNKNOWN
Classifier: Intended Audience :: Developers
Classifier: License :: OSI Approved :: GNU General Public License v2 (GPLv2)
Classifier: Operating System :: POSIX :: Linux
Classifier: Programming Language :: Python
